llm_togetherai.py
llm_togetherai-0.1.0.dist-info/licenses/LICENSE
llm_togetherai-0.1.0.dist-info/METADATA
llm_togetherai-0.1.0.dist-info/WHEEL
llm_togetherai-0.1.0.dist-info/entry_points.txt
llm_togetherai-0.1.0.dist-info/top_level.txt
llm_togetherai-0.1.0.dist-info/RECORD
