Metadata-Version: 2.4
Name: llm-togetherai
Version: 0.1.0
Summary: LLM plugin for models hosted by Together AI
Author: Rajashekar Chintalapati
License-Expression: Apache-2.0
Project-URL: Homepage, https://github.com/rajashekar/llm-togetherai
Project-URL: Changelog, https://github.com/rajashekar/llm-togetherai/releases
Project-URL: Issues, https://github.com/rajashekar/llm-togetherai/issues
Project-URL: CI, https://github.com/rajashekar/llm-togetherai/actions
Keywords: llm,ai,together,language-models,plugin
Classifier: Development Status :: 3 - Alpha
Classifier: Intended Audience :: Developers
Classifier: Programming Language :: Python :: 3
Classifier: Programming Language :: Python :: 3.9
Classifier: Programming Language :: Python :: 3.10
Classifier: Programming Language :: Python :: 3.11
Classifier: Programming Language :: Python :: 3.12
Classifier: Programming Language :: Python :: 3.13
Classifier: Topic :: Software Development :: Libraries :: Python Modules
Requires-Python: >=3.9
License-File: LICENSE
Requires-Dist: llm>=0.23
Requires-Dist: httpx
Requires-Dist: openai>=1.57.0
Provides-Extra: test
Requires-Dist: pytest; extra == "test"
Requires-Dist: pytest-recording; extra == "test"
Requires-Dist: inline-snapshot; extra == "test"
Dynamic: license-file
